django_daisy/__init__.py
django_daisy/_helpers.py
django_daisy/_version.py
django_daisy/admin.py
django_daisy/apps.py
django_daisy/logentry_admin.py
django_daisy/mixins.py
django_daisy/module_settings.py
django_daisy/fields/__init__.py
django_daisy/fields/checkbox.py
django_daisy/fields/ckeditor.py
django_daisy/fields/json_editor_field.py
django_daisy/fields/keyvalue_field.py
django_daisy/fields/summernote.py
django_daisy/fields/tags_field.py
django_daisy/fields/thousand_sep_field.py
django_daisy/locale/fa/LC_MESSAGES/django.mo
django_daisy/locale/fa/LC_MESSAGES/django.po
django_daisy/management/__init__.py
django_daisy/management/commands/__init__.py
django_daisy/management/commands/build_daisyui.py
django_daisy/static/admin/css/autocomplete.css
django_daisy/static/admin/css/calendar.css
django_daisy/static/admin/css/customized_components.css
django_daisy/static/admin/css/login.css
django_daisy/static/admin/css/vendor/select2/LICENSE-SELECT2.md
django_daisy/static/admin/css/vendor/select2/select2.css
django_daisy/static/admin/css/vendor/select2/select2.min.css
django_daisy/static/admin/fields/ckeditor_init.js
django_daisy/static/admin/fields/tags.widget.js
django_daisy/static/admin/fields/thousand_sep_field.js
django_daisy/static/admin/fields/json-editor/json_editor_init.js
django_daisy/static/admin/fields/json-editor/jsoneditor.min.js
django_daisy/static/admin/fields/keyvalue_field/script.js
django_daisy/static/admin/fields/keyvalue_field/style.css
django_daisy/static/admin/fonts/LICENSE.txt
django_daisy/static/admin/fonts/README.txt
django_daisy/static/admin/fonts/Roboto-Bold-webfont.woff
django_daisy/static/admin/fonts/Roboto-Light-webfont.woff
django_daisy/static/admin/fonts/Roboto-Regular-webfont.woff
django_daisy/static/admin/fonts/Vazir.woff2
django_daisy/static/admin/fonts/Ubuntu/UFL.txt
django_daisy/static/admin/fonts/Ubuntu/Ubuntu-Bold.ttf
django_daisy/static/admin/fonts/Ubuntu/Ubuntu-Light.ttf
django_daisy/static/admin/fonts/Ubuntu/Ubuntu-Medium.ttf
django_daisy-2.0.7.dist-info/licenses/LICENSE
django_daisy-2.0.7.dist-info/METADATA
django_daisy-2.0.7.dist-info/WHEEL
django_daisy-2.0.7.dist-info/top_level.txt
django_daisy-2.0.7.dist-info/RECORD
