Metadata-Version: 2.4
Name: django-daisy
Version: 2.0.7
Summary: A modern Django dashboard built with DaisyUI
Home-page: https://github.com/hypy13/django-daisy
Author: Hossein Yaghoubi
Author-email: Hossein Yaghoubi <hossein.yaghoubi13@gmail.com>
License: Apache-2.0
Keywords: django,admin,dashboard,daisyui,tailwindcss
Classifier: Programming Language :: Python :: 3
Classifier: License :: OSI Approved :: Apache Software License
Classifier: Operating System :: OS Independent
License-File: LICENSE
Requires-Dist: Django>=3.2
Dynamic: author
Dynamic: home-page
Dynamic: license-file
